[
  {
    "id": "cond_f_001",
    "category": "First Conditional",
    "complexity": 1,

    "question": "If it _____ (rain), we will stay at home.",
    "options": ["rains", "will rain"],
    "correctAnswer": "rains",
    "explanation": "In the IF clause use Present Simple, not future.",

    "priority": 10,
    "lastSeen": 0,
    "mistakeCount": 0
  },
  {
    "id": "cond_f_002",
    "category": "First Conditional",
    "complexity": 2,

    "question": "She will call you if she _____ (have) time.",
    "options": ["has", "will have"],
    "correctAnswer": "has",
    "explanation": "Future is used only in the main clause.",

    "priority": 10,
    "lastSeen": 0,
    "mistakeCount": 0
  }
]
